ICECipher/__init__.py
ICECipher-1.0.dist-info/LICENSE
ICECipher-1.0.dist-info/METADATA
ICECipher-1.0.dist-info/WHEEL
ICECipher-1.0.dist-info/top_level.txt
ICECipher-1.0.dist-info/RECORD
