Metadata-Version: 2.2
Name: ICECipher
Version: 1.0
Summary: ICE cipher for Python
Home-page: https://github.com/RenardDev/ICECipher
Download-URL: https://github.com/RenardDev/ICECipher/releases/latest
Author: RenardDev
Author-email: zeze839@gmail.com
License: MIT
Classifier: Development Status :: 5 - Production/Stable
Classifier: Intended Audience :: Developers
Classifier: Topic :: Software Development
Classifier: License :: OSI Approved :: MIT License
Classifier: Programming Language :: Python :: 3
License-File: LICENSE
Dynamic: author
Dynamic: author-email
Dynamic: classifier
Dynamic: download-url
Dynamic: home-page
Dynamic: license
Dynamic: summary
